MANIFEST.in
setup.cfg
setup.py
libyaz0/__init__.py
libyaz0/yaz0.py
libyaz0/yaz0_cy.pyx
libyaz0/yaz0_pyd.pyd
libyaz0.egg-info/PKG-INFO
libyaz0.egg-info/SOURCES.txt
libyaz0.egg-info/dependency_links.txt
libyaz0.egg-info/top_level.txt