Metadata-Version: 1.1
Name: libyaz0
Version: 0.5
Summary: A library for compressing/decompressing Yaz0/1 compression formats
Home-page: https://github.com/aboood40091/libyaz0
Author: AboodXD
Author-email: aboood40091@gmail.com
License: GNU General Public License v3 (GPLv3)
Download-URL: https://github.com/aboood40091/libyaz0/archive/v0.5.tar.gz
Keywords: compress,decompress,yaz0,szs,yaz1
Platform: UNKNOWN
Classifier: License :: OSI Approved :: GNU General Public License v3 (GPLv3)
Classifier: Programming Language :: Cython
Classifier: Programming Language :: Python :: 3 :: Only
Classifier: Topic :: Software Development :: Libraries :: Python Modules
Classifier: Topic :: System :: Archiving :: Compression
